sphinx_autorun/__init__.py
sphinx_autorun/pycon.py
sphinx_autorun/version.py
sphinx_autorun_ng/__init__.py
sphinx_autorun_ng/pycon.py
sphinx_autorun_ng/pycon.py.bak
sphinx_autorun_ng/version.py
sphinx_autorun_ng-1.0.0.dist-info/DESCRIPTION.rst
sphinx_autorun_ng-1.0.0.dist-info/METADATA
sphinx_autorun_ng-1.0.0.dist-info/RECORD
sphinx_autorun_ng-1.0.0.dist-info/WHEEL
sphinx_autorun_ng-1.0.0.dist-info/metadata.json
sphinx_autorun_ng-1.0.0.dist-info/top_level.txt
