Metadata-Version: 2.0
Name: sphinx-autorun-ng
Version: 1.0.0
Summary: Sphinx extension autorun
Home-page: https://gitlab.com/hobarrera/sphinx-autorun
Author: Hugo Osvaldo Barrera
Author-email: hugo@barrera.io
License: BSD
Download-URL: http://pypi.python.org/pypi/sphinx-autorun
Platform: any
Classifier: Development Status :: 4 - Beta
Classifier: Environment :: Console
Classifier: Environment :: Web Environment
Classifier: Intended Audience :: Developers
Classifier: License :: OSI Approved :: BSD License
Classifier: Operating System :: OS Independent
Classifier: Programming Language :: Python
Classifier: Topic :: Documentation
Classifier: Topic :: Utilities
Requires-Dist: Sphinx (>=0.6)
